evoke/CONTENTS.md
evoke/VERSION
evoke/Var.py
evoke/__init__.py
evoke/config_base.py
evoke/config_multi.py.example
evoke/config_site.py.example
evoke/create_app
evoke/devstart
evoke/multiserve.py
evoke/restart-multi
evoke/start-multi
evoke/stop-multi
evoke/Page/File.py
evoke/Page/Image.py
evoke/Page/Page.py
evoke/Page/__init__.py
evoke/Page/config.py
evoke/Page/evo/Page_actions.evo
evoke/Page/evo/Page_child_add.evo
evoke/Page/evo/Page_child_pages.evo
evoke/Page/evo/Page_content_header.evo
evoke/Page/evo/Page_edit_extras.evo
evoke/Page/evo/Page_edit_form.evo
evoke/Page/evo/Page_file_add.evo
evoke/Page/evo/Page_file_edit.evo
evoke/Page/evo/Page_file_list.evo
evoke/Page/evo/Page_footer.evo
evoke/Page/evo/Page_footer_extra.evo
evoke/Page/evo/Page_header.evo
evoke/Page/evo/Page_header_end.evo
evoke/Page/evo/Page_header_start.evo
evoke/Page/evo/Page_image_add.evo
evoke/Page/evo/Page_image_edit.evo
evoke/Page/evo/Page_image_list.evo
evoke/Page/evo/Page_import_form.evo
evoke/Page/evo/Page_listing.evo
evoke/Page/evo/Page_listing_footer.evo
evoke/Page/evo/Page_listing_header.evo
evoke/Page/evo/Page_navbar.evo
evoke/Page/evo/Page_options.evo
evoke/Page/evo/Page_preferences.evo
evoke/Page/evo/Page_rating.evo
evoke/Page/evo/Page_results.evo
evoke/Page/evo/Page_search_form.evo
evoke/Page/evo/Page_share.evo
evoke/Page/evo/Page_summaryimage.evo
evoke/Page/evo/Page_summarytext.evo
evoke/Page/evo/Page_view_files.evo
evoke/Page/evo/Page_view_form.evo
evoke/Page/evo/Page_view_images.evo
evoke/Page/evo/Page_view_text.evo
evoke/Page/evo/Page_view_text_summary.evo
evoke/Permit/Permit.py
evoke/Permit/__init__.py
evoke/Permit/config.py
evoke/Reset/Reset.py
evoke/Reset/__init__.py
evoke/Reset/config.py
evoke/Session/Session.py
evoke/Session/__init__.py
evoke/Session/config.py
evoke/User/User.py
evoke/User/__init__.py
evoke/User/config.py
evoke/User/evo/User_display.evo
evoke/User/evo/User_edit_form.evo
evoke-6.0.dist-info/DESCRIPTION.rst
evoke-6.0.dist-info/LICENSE.txt
evoke-6.0.dist-info/METADATA
evoke-6.0.dist-info/RECORD
evoke-6.0.dist-info/WHEEL
evoke-6.0.dist-info/metadata.json
evoke-6.0.dist-info/top_level.txt
