Metadata-Version: 2.0
Name: evoke
Version: 6.0
Summary: a simple and powerful python web framework with pythonic "evo" templating
Home-page: https://github.com/howiemac/evoke
Author: The Evoke Foundation
Author-email: howiemac@gmail.com
License: modified BSD
Keywords: development http html twisted mysql
Platform: UNKNOWN
Classifier: Development Status :: 5 - Production/Stable
Classifier: Intended Audience :: Developers
Classifier: Topic :: Software Development
Classifier: License :: OSI Approved :: BSD License
Classifier: Programming Language :: Python :: 3.6
Requires-Dist: markdown
Requires-Dist: mysqlclient
Requires-Dist: pillow
Requires-Dist: twisted
